cat_mod/__init__.py
cat_mod/catmod.py
cat_mod/utils/__init__.py
cat_mod/utils/checking_dependencies.py
cat_mod/utils/cleaning.py
cat_mod/utils/data_pipeline.py
cat_mod/utils/load_and_process_utils.py
cat_mod/utils/predicting.py
cat_mod/utils/utils.py
cat_mod-0.8.1.dist-info/LICENSE
cat_mod-0.8.1.dist-info/METADATA
cat_mod-0.8.1.dist-info/WHEEL
cat_mod-0.8.1.dist-info/top_level.txt
cat_mod-0.8.1.dist-info/RECORD
