Metadata-Version: 2.1
Name: cat-mod
Version: 0.8.1
License-File: LICENSE
Requires-Dist: numpy ==1.26.4
Requires-Dist: pandas ==2.2.2
Requires-Dist: scikit-learn ==1.5.0
Requires-Dist: tensorflow ==2.16.1
